ajaejokes/__init__.py
ajaejokes-0.1.1.dist-info/LICENSE
ajaejokes-0.1.1.dist-info/METADATA
ajaejokes-0.1.1.dist-info/WHEEL
ajaejokes-0.1.1.dist-info/RECORD
